[{"id":"7457880883","title":"新上租盘 价格可谈 石牌东法院宿舍 3 房","price":4000,"area":"70.5","orient":"朝北","rentType":"整租","rooms":"3室2厅","roomCount":3,"bathroomCount":1,"des":"品质推荐：正规户型，整套出租，3室2厅1卫，北朝向，距离地铁840米，精装修，普通住宅，有电梯","metro":"3/11/5号线","floor":"低层(共36层)","imgHashes":["5e2a4c7ad8f9cc7bec0df6fe3bc46a5d","d6b95ecef1d7ff6574f4566226f07f8e","40b7b81ecbc709b6e30bad15aecca6ba","9fe6faa6b6a79a88de9d65fa4dd7ee19","50468f0b56d876adf0dc51d8d1a77405","84bc6db036a9a8b586105a742ca75f67","da2c8801f205723c51c532b7681af7b8","06e2df490647cf15484ece9756411ce9"],"amenities":[]},{"id":"4476784662981642","title":"石牌东法院宿舍 3室2厅1卫","price":850,"area":"9","orient":"朝北","rentType":"合租","rooms":"3室2厅","roomCount":3,"bathroomCount":1,"des":"岗顶地铁口三室两厅次卧合租，精装修，暨南大学和中山三院附近，采光通风好，干净卫生，民水民电，楼下美食超市，生活便利，可短租。                          纯女生合租，其他两个房间各住一个女生，性格好，爱干净，好相处。","metro":"3/11/5号线","floor":"暂无","imgHashes":[],"amenities":[]}]