[{"id":"7430988391","title":"近芳村地铁站旁边 精装大两房 南北通透 采光通风好 拎包入住","price":3200,"area":"64","orient":"朝南","rentType":"整租","rooms":"2室2厅","roomCount":2,"bathroomCount":1,"des":"一、房源优势：  1、全明格局  2、 客厅宽敞大气；非常干净  3、 精装修 ,房屋年代：2020年  二、户型介绍：   户型：2室2厅1厨1卫1阳台 朝向：东南  格局方正 使用率非常高；  1、客厅宽敞舒适、落地阳台让充足的阳光不留余地的照进来；  2、卧室非常温馨，面积特别合理；  3、厨房宽敞，让您和家人有足够的空间展现私家厨艺；  4、 连接客厅和厨房之间是您和家人享受美味的餐厅，让您热情的招待亲朋好友。  三、社区介绍：  环境优美 适宜居住 人文素质高 物业管理完善；  1、 小区治安好；安静安全  2、 小区的，属于低密度社区，非常适宜居住；  3、 小区高，让您感受花园一","metro":"22/11/1号线","floor":"中层(共9层)","imgHashes":["206b24470583d8d13ac63ac8f42dfe31","cc02dd1e122e07eee90b10d25987f512","589857b51da0ab24911fec3fd3ff2b79","76ce86f713d06128575884d7ac229fc1","cb054e7edc98a8cf4c46cf32cfaa54aa","b77d933057f375145ae5ab1c3856fc02"],"amenities":[]},{"id":"7474597722","title":"芳村地铁站 100米电梯高层两房 余庆园 随时方便看房","price":2700,"area":"85","orient":"朝南","rentType":"整租","rooms":"2室1厅","roomCount":2,"bathroomCount":1,"des":"• 位于荔湾区芳村的余庆园，这是一套2室1厅1卫的精装修房源，朝南，采光佳。小区有电梯，容积率低，环境舒适。房屋配有冰箱、电视、洗衣机、热水器、空调、宽带、床、暖气、衣柜等，可做饭，智能门锁保障安全。整租类型，押二付一，适合长期居住。  • 周边设施齐全，步行可达白鹅潭万象城和白鹅潭华润万象城，购物便利。附近还有多个公交车站，距离22号线芳村地铁站仅267米，出行方便。此外，醉观公园和应战体育公园近在咫尺，休闲娱乐无忧。医疗方面，广州市荔湾区人民医院距离510米，就医方便。  • 我专注于荔湾区的租房服务，对坑口、花地湾、芳村等商圈非常熟悉，手头房源多，能快速帮您找到满意的家。如果您有任何疑问","metro":"22/11/1号线","floor":"高层(共9层)","imgHashes":["b5e469b2c6f860263ee39299a9a322c2","8974b47901d161078c0f726cdfe58cc1","433a6daf4fd98bfcfa3bc7cba70936a3","d68ef2a0bded36314ad99b9527c8f2f2","3e461b9753540afba674d5d600f4b3cc","a99f9802713c80be38db38019cfda9e6","b4feda4e4bb64ec10c10525f9d41f17a"],"amenities":[]}]