[{"id":"7454945941","title":"珠村地铁站 欢乐颂 珠村BRT公交站 全采光 地铁100米","price":880,"area":"43","orient":"朝南","rentType":"整租","rooms":"1室1厅","roomCount":1,"bathroomCount":null,"des":"【我们承诺】房，可押一付一。  【交通便利】东圃黄村珠村出门公交临地铁  【房屋情况】智能电子密码锁，随时带看；均摊民用水电煤；WIFI，车位可租。  【房屋设施】冰箱，空调，微波炉；书桌，台灯，大衣柜；洗衣机，热水器，居家电器，一应俱全  宜家风格装修，木地板，管家1对1服务，双周保洁，温暖家居，清新舒适，采光充足，小区环境优美，交通便利，商圈发达，欢迎您的入住。","metro":"13号线","floor":"中层(共6层)","imgHashes":["1ce3756230c15a8b8b1b748bad1d8c35","d88c8a945dd7127e2f6b42c36a757c0b","1afffaee3bf5d45f20f3f5f7fd57fbaa","c9572a132e46d041495fdf54c84bd901","7da894ea3afbdd88e37467bfc59f9077","af371c669055fa99e9031cedc2beb2e3","59ed044d44c372a9a04b9293dee7fe51","4d146bf50564293a992aebf0b3e08181"],"amenities":[]},{"id":"7469443367","title":"珠村BRT 珠村地铁13号5号线双地铁 欢乐颂 民电","price":900,"area":"40","orient":"朝南","rentType":"整租","rooms":"1室1厅","roomCount":1,"bathroomCount":null,"des":"房子环境优美,绿化充足, 入住即与精英为邻 交通便利,附近的公交：B1路、B2A路、B3路、B4路、B4B路、B5路、B6路、B7路、B15路、B16路、B17路、B18路、B19路、B20路、B27路地铁：4号线黄村站公交：B1路、B2A路、B3路、B4路、B4B路、B5路、B6路、B7路、B15路、B16路、B17路、B18路、B19路、B20路、B27路地铁：4号线黄村站, 天河区BRT直达，4号地铁线，5号线地铁 有小区房，有公寓房。 有合租，有整租。 有单间，一房，两房和三房。 有精装修有普通装修。 都是家私电器齐全，可以拎包入住！光线通风好。大路边不走巷子，安全安静。交通便捷","metro":"13号线","floor":"高层(共6层)","imgHashes":["3ae964f1b8ca9ecabe475db35cb2e62c","9dd3b0a0ff1a20a29d43d8840356134c","8f1f2e46fca6eba0efe410539ef571a5","9dc924205901dfc98e4939cfcc33c542","d34c66236373a46958024b8b4d2ab449","56e05b25666464489430bb8d0762ec9b","5eef1a6d3b45d8d9e923b243796e5e61"],"amenities":[]},{"id":"7441014645","title":"珠村地铁 欢乐颂 盈江广场 珠村brt 珠村夜市 电梯精装房","price":650,"area":"20","orient":"朝南","rentType":"整租","rooms":"1室","roomCount":1,"bathroomCount":null,"des":"【介绍】各楼层干净明亮,南北通透采光好。房内配套有席梦思大床、床头柜、沙发、空调、热水器、衣柜、茶几、抽烟机、冰箱、洗衣机、独立厨房、卫生间、超大阳台。  附近的公交：B1路、B2A路、B3路、B4路、B4B路、B5路、B6路、B7路、B15路、B16路、B17路、B18路、B19路、B20路、B27路地铁：4号线黄村站公交：B1路、B2A路、B3路、B4路、B4B路、B5路、B6路、B7路、B15路、B16路、B17路、B18路、B19路、B20路、B27路地铁：4号线黄村站,天河区BRT直达，4号地铁线，5号线地铁有小区房，有公寓房。有合租，有整租。有单间，一房，两房和三房。","metro":"13号线","floor":"高层(共7层)","imgHashes":["8669b0615f62a6c0d38cfca2ed3151dc","2eb7e8588d2bbfa96f2400c8989b12e5","a1d3ddfeea25fef6cf91d06315305792","f675b4bd787824c640273fa32df0f04b","f2c92a90695da655f904700a8658a719","556e3f921bf222d283666361cf334136","1442a586547710b8fb0d18168558c1e8"],"amenities":[]},{"id":"7468989900","title":"珠村牌坊 珠村地铁口  昇辉大厦 和安堡大厦 民电","price":900,"area":"40","orient":"东南","rentType":"整租","rooms":"1室1厅","roomCount":1,"bathroomCount":null,"des":"房子环境优美,绿化充足, 入住即与精英为邻 交通便利,附近的公交：B1路、B2A路、B3路、B4路、B4B路、B5路、B6路、B7路、B15路、B16路、B17路、B18路、B19路、B20路、B27路地铁：4号线黄村站公交：B1路、B2A路、B3路、B4路、B4B路、B5路、B6路、B7路、B15路、B16路、B17路、B18路、B19路、B20路、B27路地铁：4号线黄村站, 天河区BRT直达，4号地铁线，5号线地铁 有小区房，有公寓房。 有合租，有整租。 有单间，一房，两房和三房。 有精装修有普通装修。 都是家私电器齐全，可以拎包入住！光线通风好。大路边不走巷子，安全安静。交通便捷","metro":"13号线","floor":"高层(共7层)","imgHashes":["cc71c08a6b172b805f2b743400b93fac","d79dda59e372e36f4828c7f2e24539bf","2682f6959b5a61196c1ebc50a39e074c","92847a6624b6442864d2435e69aa1c1d","77397b939eeb534e91fbfc5431660859","13d4433b3d5f586130fee7b418f79c52"],"amenities":[]},{"id":"1925502025310220","title":"珠村大塘边塘堂街自建房 1室1厅1卫","price":698,"area":"35","orient":"南北","rentType":"整租","rooms":"1室1厅","roomCount":1,"bathroomCount":1,"des":"附近有地铁，农贸市场，BRT，公园，地铁站","metro":"13号线","floor":"中层(共8层)","imgHashes":[],"amenities":[]},{"id":"7454122294","title":"天河区珠村地铁口100米 盈江广场 欢乐颂 美林天地宜家家居","price":700,"area":"50","orient":"朝南","rentType":"整租","rooms":"1室","roomCount":1,"bathroomCount":null,"des":"为您在广州有一个温馨舒适的家！选材低碳环保，配套设施完善，拎包即可入住；  2、房间明亮方正，通风采光好，空气对流，位置安静，有独立卫生间、厨房；配有家私家电：空调，洗衣机，冰箱、热水器，油烟机，衣柜，沙发，桌椅，高档实木大床，家电网络齐全，通风采光好。小区还有全天候的楼道管理系统、出入口的电子门禁系统等；  3、温馨、精致、舒适，小资生活情调，为青年白领有良好的人际交往平台；  4、周边遍布风味小吃、夜宵及大型商场，在繁忙的工作之余，给你带来丰富的休闲享受；  5、随时入住，随时欢迎您的来电：  6.贴心的带看服务，根据需求推荐更多的房子  58可能无法及时回复，可以直接来电，随时看房","metro":"13号线","floor":"中层(共8层)","imgHashes":["f1b8e6263a8d829123bbe4770d967662","88537455875b74c9d72c65583acba8c5","c7716b1baa66d04bd6d437742f922fee","75a32530d7a050f465fd8b214872cee3","1ce6bcc551bd3a081d0ba7140308ad6b","f28bcd4db94e2298440a588fa4a3d197","03fca5b94f1cbd8ece3b469370e59fae"],"amenities":[]},{"id":"7442822437","title":"天河珠村 东圃地铁 东圃大马路 中山大道 科韵路 天河公园","price":650,"area":"23","orient":"朝南","rentType":"整租","rooms":"1室","roomCount":1,"bathroomCount":null,"des":"天天河珠村地铁13号线，黄村地铁4号线21号线，吉山，东圃宦溪，三溪地铁站5号线，大观南路21号线  周边设施齐全，交通完善、出行便捷、环境优越，所在的城区配套日益成熟，购物、娱乐、美食、休闲一应俱全  房源介绍：  1.房子是舒适的一室户，南北通透，空气流通，阳光充足  2、配有基础的家具、全新海尔空调、全新热水器..光纤上网、大衣柜、洗衣机、席梦思大床、床头柜衣柜、电脑桌梳妆台、沙发茶几、独立洗手间.独立大阳台，拎包入住，朝向好，阳光非常充足，面积使用率超高  3、楼距大，物业管理严格，干净、安全人文素质高，特别宜居  4、通宽敞明亮，干净清爽，家具家电齐全，拎包入住，温馨的小窝，给你的小","metro":"13号线","floor":"高层(共7层)","imgHashes":["d2cdd3595c18e663f68a750664e4cb27","0dca8184103a6451975771dc1e7b09ad","cc6612d98b31717d42fcb00f618f1167","38987008915143a4a3349b14a75ba4f0","76aecf7ed8ce141c63c9627b0d6de45b","5b6821209bd48f2c815a2928ff0fbfba"],"amenities":[]},{"id":"7421183663","title":"珠村地铁站 欢乐颂 金碧世纪花园 全采光 地铁200米 精装","price":650,"area":"39","orient":"朝南","rentType":"整租","rooms":"1室","roomCount":1,"bathroomCount":null,"des":"【我们承诺】房，可押一付一。  【交通便利】东圃黄村珠村出门公交临地铁  【房屋情况】智能电子密码锁，随时带看；均摊民用水电煤；WIFI，车位可租。  【房屋设施】冰箱，空调，微波炉；书桌，台灯，大衣柜；洗衣机，热水器，居家电器，一应俱全  宜家风格装修，木地板，管家1对1服务，双周保洁，温暖家居，清新舒适，采光充足，小区环境优美，交通便利，商圈发达，欢迎您的入住。","metro":"13号线","floor":"共2层","imgHashes":["2ccc16727c346f1627180ad9a002e75f","279ca5e3e039cfe1154c01a0db599b21","a32869d7f9eb21eca5576553de6ae1ee","174499fccec76388705e8f2899f198e2","7aae2c1c79eec1e3c4c5bba6d159e142","c21c5f785bfce88b01f9019cf443db5d","49d04b6647a6e231d32618f265c830ab","9a1381782578e1b62f289a6ade6b8e0d"],"amenities":[]},{"id":"7410146416","title":"地铁旁100米 带小院子大单间 在家可直接钓鱼 养花种草养宠","price":680,"area":"56","orient":"朝东","rentType":"整租","rooms":"1室","roomCount":1,"bathroomCount":null,"des":"房子环境优美,绿化充足,入住即与精英为邻交通便利,附近的公交:B1路、B2A路、B3路、B4路、B4B路、B5路、 B6路、B7路、B15路、B16路、B17路、B18路、B19路、 B20路、B27路地铁:4号线黄村站公交:B1路、B2A路、B3路、B4路、B4B路、B5路、B6路、B7路、B15路、B16路、B17路、B18路、B19路、B20路、B27路地铁:4号线黄村站,天河区BRT直达，4号地铁线，5号线地  铁有小区房，有公寓房。有合租，有整租。有单间，一房，两房和三房。有精装修有普通装修。都是家私电器齐全，可以拎包入住!光线通风好。大路边不走巷子安仝  安静。交通便捷","metro":"13号线","floor":"低层(共6层)","imgHashes":["2be78b51e7746fb109fd396b75437072","c0dc138c825e8e93671a2706d9f09722","222a6047218682e38872ce12694dfeb7","6c12f629baf3d25c73a5b5ded34eb824","abd8d4ec347f64e62be6f9c9b0a7b4bd","793253e2b8372855f2af52ad4fad71b8"],"amenities":[]},{"id":"7408022761","title":"天河珠村地铁 13号线 近地铁 中兴花园 欢乐颂","price":880,"area":"55","orient":"朝南","rentType":"整租","rooms":"1室1厅","roomCount":1,"bathroomCount":null,"des":"天河区黄村，珠村，吉山，东圃宦溪，三溪地铁站，大观南路，  周边设施齐全，交通完善、出行便捷、环境优越，所在的城区配套日益成熟，购物、娱乐、美食、休闲一应俱全。  房源介绍：  1.房子是舒适的一室户，南北通透，空气流通，阳光充足。  2、配有基础的家具、全新海尔空调、全新热水器..光纤上网、大衣柜、洗衣机、席梦思大床、床头柜、衣柜、电脑桌、梳妆台、沙发、茶几、独立洗手间.独立大阳台.拎包入住....朝向好，阳光非常充足，面积使用率超高。  3、楼距大，物业管理严格，干净、安全人文素质高，特别宜居。  4、通宽敞明亮，干净清爽，家具家电齐全，拎包入住，温馨的小窝，给你的小家带来归属感。","metro":"13号线","floor":"高层(共6层)","imgHashes":["921b596b51148d3c934057b302bce803","ba025a3ca074a5a5e859cbfd452f38ac","e971f73f1ca039e11dffb904c4d14da8","b0c0a63a8ac9731b84d3357e608abcb3","ecba344f29b9f6044405d610ca11cce3","af76396bd8c8dee4903df52778eacb04","39b584b9e6e95e87f73df90c5dfc786c"],"amenities":[]},{"id":"7442819417","title":"天河珠村地铁 珠村牌坊 两房一厅 阳光好 不走巷子","price":1000,"area":"45","orient":"朝南","rentType":"整租","rooms":"2室1厅","roomCount":2,"bathroomCount":null,"des":"天天河珠村地铁13号线，黄村地铁4号线21号线，吉山，东圃宦溪，三溪地铁站5号线，大观南路21号线  周边设施齐全，交通完善、出行便捷、环境优越，所在的城区配套日益成熟，购物、娱乐、美食、休闲一应俱全  房源介绍：  1.房子是舒适的一室户，南北通透，空气流通，阳光充足  2、配有基础的家具、全新海尔空调、全新热水器..光纤上网、大衣柜、洗衣机、席梦思大床、床头柜衣柜、电脑桌梳妆台、沙发茶几、独立洗手间.独立大阳台，拎包入住，朝向好，阳光非常充足，面积使用率超高  3、楼距大，物业管理严格，干净、安全人文素质高，特别宜居  4、通宽敞明亮，干净清爽，家具家电齐全，拎包入住，温馨的小窝，给你的小","metro":"13号线","floor":"高层(共7层)","imgHashes":["321a004a38c5bfe19d7bf06554491309","051f120090ea0592c7ce1a232a4dd345","cfb421a2122dbaa98a25af55f5757946","07276e4b3ef1e4a72051366600d625c4","089e2f60acc197643c8e8c315ea80e7a","f1424a3922712f74074d4cfc54df36b8","7857bd778d0c5be389f1c9f4c28764bc"],"amenities":[]},{"id":"7406805277","title":"13号线 珠村地铁 欢乐颂 珠村牌坊 一房一厅 近地铁采光好","price":880,"area":"45","orient":"朝南","rentType":"整租","rooms":"1室1厅","roomCount":1,"bathroomCount":null,"des":"天河区黄村，珠村，吉山，东圃宦溪，三溪地铁站，大观南路，  周边设施齐全，交通完善、出行便捷、环境优越，所在的城区配套日益成熟，购物、娱乐、美食、休闲一应俱全。  房源介绍：  1.房子是舒适的一室户，南北通透，空气流通，阳光充足。  2、配有基础的家具、全新海尔空调、全新热水器..光纤上网、大衣柜、洗衣机、席梦思大床、床头柜、衣柜、电脑桌、梳妆台、沙发、茶几、独立洗手间.独立大阳台.拎包入住....朝向好，阳光非常充足，面积使用率超高。  3、楼距大，物业管理严格，干净、安全人文素质高，特别宜居。  4、通宽敞明亮，干净清爽，家具家电齐全，拎包入住，温馨的小窝，给你的小家带来归属感。","metro":"13号线","floor":"高层(共7层)","imgHashes":["13646249d54f010322e792d7f517e6b1","a47517b673c6732bfa9ec15d9f8986f1","970fdb75c9acbb4df9eaf6ce79a98ee3","fa439ce86efd0e7fd9fd83b19a9454d7","7f3a28442f6790fde24102bb11bfffa4","12aed266ea70a6efb1b6f153cbaae7b7","a7b6152a6bf44419fb30fbfc397ccdcb","5e6c35b9766a8d407efda60267d433e3"],"amenities":[]}]