[{"id":"7478622464","title":"海珠区江泰路泰沙路凤阳东晓南南洲瑞宝精装修单间拎包入住采光好","price":1600,"area":"25","orient":"朝南","rentType":"整租","rooms":"1室","roomCount":1,"bathroomCount":null,"des":"一、位置：公寓位于海珠区江泰路A出口步行600米，大马路边。  二、公寓是全新装修的，家具家电都是定制款，全部都是新的，还没人用过。  三、我们的房子分别有：单间套房，一房一厅。我们是专注租房行业的，所以每个房间的格局以及配套都比较合理齐全。所有房间都有带独立大阳台，独立厨房，独立卫生间。  四、配套：我们的公寓已经做到拎包入住条件，为你省去布置新家的烦恼。房间配置：床，衣柜，沙发，茶几，电脑桌，椅子，收纳柜，电视柜，空调，热水器，抽烟机，冰箱，洗衣机等，所有配套都是全新。  五、生活：公寓楼下就有生活超市，小吃，附近有菜市场等，日常生活非常方便。一户一卡门禁管理，安全非常有保障！","metro":"11/10/2/8号线","floor":"高层(共6层)","imgHashes":["30fb53dd71209727b1f906088575f2d7","d403994e7a5ecee06a21e6b68ef75f32","627ed707c288ca71a823362c1a4e84f2","2f4a6dbde9ac859ccf4aa5f52533a01a","e5b8ef5e94b3d4878bb649192765f0fa"],"amenities":[]},{"id":"7473907768","title":"毕业季促销！2号线11号线近万科里中大纺织城电梯健身房押一","price":1599,"area":"30","orient":"朝南","rentType":"整租","rooms":"1室1厅","roomCount":1,"bathroomCount":null,"des":"与之城市青年之家是一个为在这个城市中奋斗的青年人群提供租住咨询服务、房源查找服务、社群服务的租房平台。  与之青年希望帮您租的不只是房子，更是一个心安的家。  房源覆盖区域广（白云、海珠、越秀、番禺、天河、荔湾都有房子）同时与之还有自身的托管直营门店，与之青年以专业和热情的服务，为解决房间空置问题，物业管理问题，为租客提供找房/议价/房屋带看服务，协调租户关系，帮住租客维权。  与之：与你、与我、与他；让租住生活变得更加美好！","metro":"11/10/2/8号线","floor":"低层(共9层)","imgHashes":["4f53605ff9f109b2c21d8a3ff6567385","3b3ac17537118d793385aea2a1018228","2a6d37bc9bc80591960b6ee97537f609","041e42689297360de6ed69f1fd0c8c56","0324e5974084bd425a94f78e20f48833","80c1f36c9b7fe021bcb22dbc8b2d7c95","3acf60bf98b7c5395fe8d8bdd8b15a3b"],"amenities":[]},{"id":"7465406514","title":"11号线 江泰路 五凤 双地铁 电梯一室一厅 民水电拎包入住","price":1700,"area":"40","orient":"朝南","rentType":"整租","rooms":"1室1厅","roomCount":1,"bathroomCount":1,"des":"非常感谢您的光临！让您在繁忙的城市生活中找到家的温暖。  【地理位置】  所属区域是海珠区，位于金紫里直街22,23号，附近是东晓南商圈。  【户型面积】  出租南向1室1厅1卫，电梯房，为您提供舒适明亮的生活环境。  【家具家电】  配备齐全，设施完善，冰箱、洗衣机、热水器等设施一应俱全，宽带接入方便快捷，让您享受高速网络带来的便利。可做饭，油烟机，厨房设施齐全，让您享受烹饪的乐趣。  【周边配套】  此房源周边生活便利，佳南平价超市(金紫里直街店)距离仅40米，还有多个超市选择。附近还有广州致友医院，距离696米，为您的健康保驾护航。  有意向请随时咨询我~","metro":"11/10/2/8号线","floor":"低层(共9层)","imgHashes":["5b14e1ba4fb52dd15d8508eb3ef341ef","8a78f8e63bacf1a1890cbff5337292c0","d79cd388141f99d8cc783b63774eb45e","81055cf8b25eec1b9bf3729a9b18a66b","93c0b87db4375a0ec8895b75b6ca20a0","86adebdffc80d158308e0262ede18d96","e185f93bc132df2b402f9f05ddfa667d","559baf6884555dfbdee4e7dcb02bd0b2"],"amenities":[]},{"id":"7473868490","title":"2号线江泰路 近地铁 近万科里 精装电梯采光单间 带有健身房","price":1500,"area":"25","orient":"朝南","rentType":"整租","rooms":"1室1厅","roomCount":1,"bathroomCount":null,"des":"所有房源真实，房源图片兼为精心挑选过的实拍图，公寓  1.【房型优势】：单间、大单间、LOFT风格、一房一厅、两房一厅、三房一厅可做员工宿舍.  2.【交通便利】：购物方便，美食多多  3.【省心入住】拎包入住、光线充足、环境优雅，风格时尚，专业的管家服务及安保服务，长租短租兼可.  4.【安全配置】公寓配有24小时安保，停车方便，24小时门禁，保障乐友的人身安全，公寓配置免的24小时的共享空间供青年朋友们、娱乐、休闲、游戏，社交等  5.【周边配套】周边有各种风味的美食和休闲娱乐之处，充  我们本着客户价值第一的服务理念，随时欢迎您的加入。","metro":"11/10/2/8号线","floor":"高层(共9层)","imgHashes":["9e7df16c0726f6a995b1f9764930c075","ed226633ede51a99719cb47c0bf89186","2cb6a2acf825362d0a835851ce12c197","fb958c25b8e39905df32ac015209f264","c8fc8f3ca7343b2ca6e79448ab7ef1a9","ea92043a2fad3dc14691dcbb0dd65d79","681d0582162a4928a1eb0f38d88dbfe9","d71e3faa555e45cc2d122f77845f845a"],"amenities":[]},{"id":"7471467617","title":"海珠区中大，江泰路，泰沙路大单间带阳台，拎包入住，家电齐全","price":1600,"area":"28","orient":"朝南","rentType":"整租","rooms":"1室","roomCount":1,"bathroomCount":null,"des":"一、位置：公寓位于海珠区江泰路A出口步行600米，大马路边。 二、公寓是全新装修的，家具家电都是定制款，全部都是新的，还没人用过。 三、我们的房子分别有：单间套房，一房一厅。我们是专注租房行业的，所以每个房间的格局以及配套都比较合理齐全。所有房间都有带独立大阳台，独立厨房，独立卫生间。 四、配套：我们的公寓已经做到拎包入住条件，为你省去布置新家的烦恼。房间配置：床，衣柜，沙发，茶几，电脑桌，椅子，收纳柜，电视柜，空调，热水器，抽烟机，冰箱，洗衣机等，所有配套都是全新。 五、生活：公寓楼下就有生活超市，小吃，附近有菜市场等，日常生活非常方便。一户一卡门禁管理，安全非常有保障！","metro":"11/10/2/8号线","floor":"中层(共7层)","imgHashes":["71b597840d4f8774bbddb0dfc03f147e","feff17b2eff87108ee3fc2eb681dcff3","b42e4b1d6d43a24d015eaee00af52e1f","d94c00be6a2e586fd2f8e2613422802a","8884a1702d72a50e0c42ca44292c26fe","918e11822bc8afc93ddfe5627e2f176b","7317bf9fe1a2da90c73e4222248a968d"],"amenities":[]},{"id":"7465605346","title":"海珠区押一付一 独立大阳台 近万科里 楼下美食一条街 民电","price":1800,"area":"40","orient":"朝南","rentType":"整租","rooms":"1室1厅","roomCount":1,"bathroomCount":1,"des":"• 位于海珠区东晓南商圈的金紫里直街小区，这里有一套1室1厅1卫的精装修房源整租。房子朝南，采光佳，带电梯，适合单身人士或小情侣居住。房屋配有齐全，包括冰箱、电视、洗衣机、热水器、空调等，还有可做饭的厨房，智能门锁保障安全，生活便利。  • 交通方面，距离11号线五凤地铁站927米，10号线五凤地铁站943米，出行无忧。附近还有多个公交站点，如蓝天中学(165米)、五凤乡(173米)等，方便您的日常出行。  • 生活配套方面，步行可达佳南平价超市(金紫里直街店)(40米)，购物非常方便。此外，广州致友医院距离仅696米，医疗资源近在咫尺。  • 付款方式灵活，押一付一，减轻您的经济压力。如果您","metro":"11/10/2/8号线","floor":"中层(共8层)","imgHashes":["417cf3f1f540d5ee83fb471b7b79093a","6ab12a6c8f0b9528322deb765726950d","e5e00be2977b49be473bda626eac3ab8","7f5642240c8ffb028d31e08d0669a5f4","e1dccf56640a11a0726ca2c21e72578d","5ed16ff5afcf7fc81b0ca4cdb7f82162","713693d51b7036bd5ca43498ba0a2f33","637902af1311eb434457669fcb409e1f"],"amenities":[]},{"id":"7478620715","title":"江泰路，中大布匹市场，东晓南，南洲，泰沙路，五凤乡公交站单间","price":1500,"area":"28","orient":"朝南","rentType":"整租","rooms":"1室","roomCount":1,"bathroomCount":null,"des":"一、位置：公寓位于海珠区江泰路A出口步行600米，大马路边。  二、公寓是全新装修的，家具家电都是定制款，全部都是新的，还没人用过。  三、我们的房子分别有：单间套房，一房一厅。我们是专注租房行业的，所以每个房间的格局以及配套都比较合理齐全。所有房间都有带独立大阳台，独立厨房，独立卫生间。  四、配套：我们的公寓已经做到拎包入住条件，为你省去布置新家的烦恼。房间配置：床，衣柜，沙发，茶几，电脑桌，椅子，收纳柜，电视柜，空调，热水器，抽烟机，冰箱，洗衣机等，所有配套都是全新。  五、生活：公寓楼下就有生活超市，小吃，附近有菜市场等，日常生活非常方便。一户一卡门禁管理，安全非常有保障！","metro":"11/10/2/8号线","floor":"高层(共6层)","imgHashes":["a53534dddf397222b0007f02e5978e6c","ce05450b05d4563a02d898582122ed29","9b7f5f3ea87ef1cdff7c7bb7be31b8bd","faae7b10677dc7b5f19d07deecfa918b","758172911122c0d142d60d7bdcc9e36f","790d5bfeae514bbfc6ce032e6e7c6ee7","fe5755747639e3865867019f37c31815"],"amenities":[]},{"id":"7473898211","title":"毕业季促销！2号线11号线近万科里中大纺织城电梯健身房押一","price":1400,"area":"30","orient":"朝南","rentType":"整租","rooms":"1室1厅","roomCount":1,"bathroomCount":null,"des":"与之城市青年之家是一个为在这个城市中奋斗的青年人群提供租住咨询服务、房源查找服务、社群服务的租房平台。  与之青年希望帮您租的不只是房子，更是一个心安的家。  房源覆盖区域广（白云、海珠、越秀、番禺、天河、荔湾都有房子）同时与之还有自身的托管直营门店，与之青年以专业和热情的服务，为解决房间空置问题，物业管理问题，为租客提供找房/议价/房屋带看服务，协调租户关系，帮住租客维权。  与之：与你、与我、与他；让租住生活变得更加美好！","metro":"11/10/2/8号线","floor":"中层(共9层)","imgHashes":["9adf4566d3c598d44aba149759a46eb2","796a67575805b5b93a2dbc7379ef4981","3ed1c1bc887db89d5edc5a890c73a8f3","942992529ecfa72ee3be1cbeaa50a838","488a523ca9320db236d840a9231b1ab4","f80233cd5200adafc0536905f553cd29","1c823a7d7632e5ab73e6a8315d2586e3","2eb0d656cf04302cb8220d9774125895"],"amenities":[]},{"id":"7465400231","title":"江泰路 精装电梯大单间 民水电 可短租 实图实价 拎包入住","price":1500,"area":"35","orient":"朝南","rentType":"整租","rooms":"1室1厅","roomCount":1,"bathroomCount":1,"des":"非常感谢您的光临！让您在繁忙的城市生活中找到家的温暖。  【地理位置】  位于海珠区金紫里直街22,23号，属于东晓南商圈。  【户型面积】  出租1室1厅1卫南向卧室，带电梯，采光好。  【家具家电】  配备齐全，设施完善，让您享受高品质的生活。冰箱、洗衣机、热水器、宽带一应俱全，还有可做饭的厨房，油烟机、灶具等设施齐全，满足您的生活需求。  【周边配套】  此房源周边生活便利，步行可达佳南平价超市(金紫里直街店)和憨豆超市(金紫里店)，距离广州致友医院仅696米。  有意向请随时咨询我~","metro":"11/10/2/8号线","floor":"低层(共9层)","imgHashes":["f0b1bc7bc132c786505b44874481b52e","65aa35b969f91c9758200cee9f5922aa","5ecd6837cc4eb925f6716cda551aa3d1","cf7967456b98971710035fdb4aa333ec","ca219b7cb1f55c329cc1394c205220e2","0502e9646c8e33eb64152dc40ef89afd","4390d6adc02751f561bb8873a96e475f"],"amenities":[]},{"id":"7471458094","title":"海珠区，，江泰路，泰沙路，东晓南，江南西，瑞宝，拎包入住","price":1580,"area":"28","orient":"朝南","rentType":"整租","rooms":"1室","roomCount":1,"bathroomCount":null,"des":"一、位置：公寓位于海珠区江泰路A出口步行600米，大马路边。 二、公寓是全新装修的，家具家电都是定制款，全部都是新的，还没人用过。 三、我们的房子分别有：单间套房，一房一厅。我们是专注租房行业的，所以每个房间的格局以及配套都比较合理齐全。所有房间都有带独立大阳台，独立厨房，独立卫生间。 四、配套：我们的公寓已经做到拎包入住条件，为你省去布置新家的烦恼。房间配置：床，衣柜，沙发，茶几，电脑桌，椅子，收纳柜，电视柜，空调，热水器，抽烟机，冰箱，洗衣机等，所有配套都是全新。 五、生活：公寓楼下就有生活超市，小吃，附近有菜市场等，日常生活非常方便。一户一卡门禁管理，安全非常有保障！","metro":"11/10/2/8号线","floor":"中层(共6层)","imgHashes":["0499e76dec0e67accedb56deece8c7ab","121c47f4f6ab3a9d57569da7240a8984","c497f84f5973c373b274e77d5b25b6c3","c0fbb13caf17c49608416784f9f3f1a5","b308769ed271f8600a22711ea2a82410","0d0d5d038470dd4605e7f4a495b667cb","96322ac7a0e4761c5e7fcb648ca1c91e"],"amenities":[]},{"id":"7465603929","title":"江泰路近东晓南纺织城 超大阳台一房 带电梯押一付一 民电","price":1680,"area":"35","orient":"朝南","rentType":"整租","rooms":"1室1厅","roomCount":1,"bathroomCount":1,"des":"【房源信息】这套1室1厅1卫的房子位于金紫里直街22、23号，精装修，带电梯，朝南，采光很好。房间配有冰箱、电视、洗衣机、热水器、空调、宽带、床、暖气、衣柜等，可做饭，智能门锁，油烟机齐全，拎包即住。付款方式押一付一，适合单身或小情侣居住。  【交通便利】附近有多个公交站，如蓝天中学(165米)、五凤乡(173米)等，距离五凤地铁站（11号线）927米，东晓南地铁站（10号线）1235米，出行方便。  【生活配套】楼下就有佳南平价超市，购物便利。附近还有广州致友医院，距离696米，医疗有保障。  【租赁服务】我专注于海珠区的租赁服务，对东晓南商圈非常熟悉，从业3-5年，欢迎随时联系看房。","metro":"11/10/2/8号线","floor":"高层(共8层)","imgHashes":["cb595bbaa5aab9cd9051c914f484a666","1e6042ef1e73064461aa455ff45a0237","90b7b8c9a635f9ef5dead43f95538861","0301e89b26e97ee9b5b98eaaa214104f","e8cc13fa0b87ee300365ad32cd3ca3aa","e847d743bdcb7b4705900f9c6177ddce","28e14b8b75fffae798c19aca81b0d301","db67f9915cc6c7f673082e808b69344e"],"amenities":[]},{"id":"7409804733","title":"中大，轻纺城，瑞宝，东晓南，金紫里美食街押一付一一年租大单间","price":1500,"area":"25","orient":"朝南","rentType":"整租","rooms":"1室","roomCount":1,"bathroomCount":null,"des":"一、位置：公寓位于海珠区江泰路A出口步行600米，大马路边。  二、公寓是全新装修的，家具家电都是定制款，全部都是新的，还没人用过。  三、我们的房子分别有：单间套房，一房一厅。我们是专注租房行业的，所以每个房间的格局以及配套都比较合理齐全。所有房间都有带独立大阳台，独立厨房，独立卫生间。  四、配套：我们的公寓已经做到拎包入住条件，为你省去布置新家的烦恼。房间配置：床，衣柜，沙发，茶几，电脑桌，椅子，收纳柜，电视柜，空调，热水器，抽烟机，冰箱，洗衣机等，所有配套都是全新。  五、生活：公寓楼下就有生活超市，小吃，附近有菜市场等，日常生活非常方便。一户一卡门禁管理，安全非常有保障！","metro":"11/10/2/8号线","floor":"中层(共6层)","imgHashes":["226723818363a33c8fd58fe393471ef0","c93295a2155bf78f49eb740aec12e1ed","6524fb6b80b59a2be3cab6ec4972214c","b4832df713fc9c6e466c93669ece68c2","34b38cda5afd7a1bc5da0752b9ccfd0f","ddb0733a0adc567ebad36621d3dfd860","8df53bc0436d1adfd3891396714a8180"],"amenities":[]},{"id":"7471465847","title":"海珠区中大布匹批发市场，江南西，金紫里美食街，大阳台押一付一","price":1600,"area":"28","orient":"朝南","rentType":"整租","rooms":"1室","roomCount":1,"bathroomCount":null,"des":"一、位置：公寓位于海珠区江泰路A出口步行600米，大马路边。 二、公寓是全新装修的，家具家电都是定制款，全部都是新的，还没人用过。 三、我们的房子分别有：单间套房，一房一厅。我们是专注租房行业的，所以每个房间的格局以及配套都比较合理齐全。所有房间都有带独立大阳台，独立厨房，独立卫生间。 四、配套：我们的公寓已经做到拎包入住条件，为你省去布置新家的烦恼。房间配置：床，衣柜，沙发，茶几，电脑桌，椅子，收纳柜，电视柜，空调，热水器，抽烟机，冰箱，洗衣机等，所有配套都是全新。 五、生活：公寓楼下就有生活超市，小吃，附近有菜市场等，日常生活非常方便。一户一卡门禁管理，安全非常有保障！","metro":"11/10/2/8号线","floor":"高层(共7层)","imgHashes":["2413b9ca3b2f868f41ac17d0844751dd","68ba917969b4e10f540945c159b12e6d","bff98e6b79c3017772393c139206332e","39d0eed7951b85ff7b21296c9f6fcac7","902c1caf2104d7d3d120423bacc121af","ebb1f1d6d0a1cd35e46803c1a928230e","68c94b4ae90a7e302d02bf0378824652"],"amenities":[]},{"id":"7478736619","title":"中大布匹市场，轻纺城，瑞宝，东晓南，江南西，金紫里复试一楼","price":1400,"area":"30","orient":"朝南","rentType":"整租","rooms":"1室1厅","roomCount":1,"bathroomCount":null,"des":"一、位置：公寓位于海珠区江泰路A出口步行600米，大马路边。  二、公寓是全新装修的，家具家电都是定制款，全部都是新的，还没人用过。  三、我们的房子分别有：单间套房，一房一厅。我们是专注租房行业的，所以每个房间的格局以及配套都比较合理齐全。所有房间都有带独立大阳台，独立厨房，独立卫生间。  四、配套：我们的公寓已经做到拎包入住条件，为你省去布置新家的烦恼。房间配置：床，衣柜，沙发，茶几，电脑桌，椅子，收纳柜，电视柜，空调，热水器，抽烟机，冰箱，洗衣机等，所有配套都是全新。  五、生活：公寓楼下就有生活超市，小吃，附近有菜市场等，日常生活非常方便。一户一卡门禁管理，安全非常有保障！","metro":"11/10/2/8号线","floor":"低层(共6层)","imgHashes":["df9d2bcde9fdb7e6134a5046de06c167","c2299ec99ea43429debba781c727fc7f","8ba07a09bda6a635f051a85e257e1ce4","ffe320e7d7fad2d81b8088f4960ca1ec","4c09b53babe5bce1c6739d13787611c7","7a3af5750ee3670688f8f852d39378ad","46662d35dc16868820d1bd3ca1833884"],"amenities":[]},{"id":"7456880926","title":"海珠区江泰路泰沙路金紫里瑞宝东晓南大阳台拎包入住无遮挡采光好","price":1600,"area":"28","orient":"朝南","rentType":"整租","rooms":"1室","roomCount":1,"bathroomCount":null,"des":"一、位置：公寓位于海珠区江泰路A出口步行600米，大马路边。  二、公寓是全新装修的，家具家电都是定制款，全部都是新的，还没人用过。  三、我们的房子分别有：单间套房，一房一厅。我们是专注租房行业的，所以每个房间的格局以及配套都比较合理齐全。所有房间都有带独立大阳台，独立厨房，独立卫生间。  四、配套：我们的公寓已经做到拎包入住条件，为你省去布置新家的烦恼。房间配置：床，衣柜，沙发，茶几，电脑桌，椅子，收纳柜，电视柜，空调，热水器，抽烟机，冰箱，洗衣机等，所有配套都是全新。  五、生活：公寓楼下就有生活超市，小吃，附近有菜市场等，日常生活非常方便。一户一卡门禁管理，安全非常有保障！","metro":"11/10/2/8号线","floor":"中层(共7层)","imgHashes":["7707e9c066a7cb29b1ee6ee47a80aefa","60dbbfd13fe74ea458fc81a6beead8ad","49d5bde48d4fbfbe3e1f3ebe8a05eccc","5c8eaaf41fc8f72a05dd30c2bdadc11f","bfac86f42587b88b3ef266fe237c8a5f","08cb0f1483afc50d50ddd48c7541d194","50056c53c9767402aa5303ecba70d632"],"amenities":[]},{"id":"7478618134","title":"江泰路泰沙路金紫里直街一房一厅精装修，押一付一8个月起租","price":1700,"area":"45","orient":"朝南","rentType":"整租","rooms":"1室1厅","roomCount":1,"bathroomCount":null,"des":"一、位置：公寓位于海珠区江泰路A出口步行600米，大马路边。  二、公寓是全新装修的，家具家电都是定制款，全部都是新的，还没人用过。  三、我们的房子分别有：单间套房，一房一厅。我们是专注租房行业的，所以每个房间的格局以及配套都比较合理齐全。所有房间都有带独立大阳台，独立厨房，独立卫生间。  四、配套：我们的公寓已经做到拎包入住条件，为你省去布置新家的烦恼。房间配置：床，衣柜，沙发，茶几，电脑桌，椅子，收纳柜，电视柜，空调，热水器，抽烟机，冰箱，洗衣机等，所有配套都是全新。  五、生活：公寓楼下就有生活超市，小吃，附近有菜市场等，日常生活非常方便。一户一卡门禁管理，安全非常有保障！","metro":"11/10/2/8号线","floor":"低层(共7层)","imgHashes":["50a79c86c68138207bbc9fe0e393c39c","daab464d4ba3d89cd24b81e5ea60152c","0a68865cf4bd1af1b2077c5160462a14","90b122dce202ca3c17527cc47958072d","5e1739f9928f00d556669defd0b067d8","8e171e92f648dfc0f32dfe4581def109","85b633227ef206488078223130cf1a79"],"amenities":[]},{"id":"7456880887","title":"江泰路泰沙路金紫里瑞宝东晓南押一付一，一房一厅大阳台拎包入住","price":1880,"area":"45","orient":"朝南","rentType":"整租","rooms":"1室1厅","roomCount":1,"bathroomCount":null,"des":"一、位置：公寓位于大石A出口步行300米，大马路边。  二、公寓是全新装修的，家具家电都是定制款，全部都是新的，还没人用过。  三、我们的房子分别有：单间套房，一房一厅。我们是专注租房行业的，所以每个房间的格局以及配套都比较合理齐全。所有房间都有带独立大阳台，独立厨房，独立卫生间。  四、配套：我们的公寓已经做到拎包入住条件，为你省去布置新家的烦恼。房间配置：床，衣柜，沙发，茶几，电脑桌，椅子，收纳柜，电视柜，空调，热水器，抽烟机，冰箱，洗衣机等，所有配套都是全新。  五、生活：公寓楼下就有生活超市，小吃，附近有菜市场等，日常生活非常方便。一户一卡门禁管理，安全非常有保障！","metro":"11/10/2/8号线","floor":"中层(共6层)","imgHashes":["e634133645f0f8c640304d5cb6b9e092","12a2e0e46f66d712b1b5ded3b7e2d5f2","77f5f87197ceefe16bcffbc8b5920284","bf53e40deb67cb35d57c73d9f410526e","7e2387cad55e5638d95b9b25d7f99ffe","0e4d01181a1297466bf691c47a1f7b61","07c8efad1ce7aacae400d406cc583d12"],"amenities":[]},{"id":"7471648869","title":"海珠区，，江泰路，泰沙路，东晓南，江南西，瑞宝，拎包入住","price":1580,"area":"28","orient":"朝南","rentType":"整租","rooms":"1室","roomCount":1,"bathroomCount":null,"des":"一、位置：公寓位于海珠区江泰路A出口步行600米，大马路边。 二、公寓是全新装修的，家具家电都是定制款，全部都是新的，还没人用过。 三、我们的房子分别有：单间套房，一房一厅。我们是专注租房行业的，所以每个房间的格局以及配套都比较合理齐全。所有房间都有带独立大阳台，独立厨房，独立卫生间。 四、配套：我们的公寓已经做到拎包入住条件，为你省去布置新家的烦恼。房间配置：床，衣柜，沙发，茶几，电脑桌，椅子，收纳柜，电视柜，空调，热水器，抽烟机，冰箱，洗衣机等，所有配套都是全新。 五、生活：公寓楼下就有生活超市，小吃，附近有菜市场等，日常生活非常方便。一户一卡门禁管理，安全非常有保障！","metro":"11/10/2/8号线","floor":"中层(共6层)","imgHashes":["0499e76dec0e67accedb56deece8c7ab","121c47f4f6ab3a9d57569da7240a8984","c497f84f5973c373b274e77d5b25b6c3","c0fbb13caf17c49608416784f9f3f1a5","b308769ed271f8600a22711ea2a82410","0d0d5d038470dd4605e7f4a495b667cb","96322ac7a0e4761c5e7fcb648ca1c91e"],"amenities":[]},{"id":"7456527388","title":"海珠区中大国际市场，东晓南，瑞宝，江泰路，金紫里，泰沙路单间","price":1500,"area":"25","orient":"朝南","rentType":"整租","rooms":"1室","roomCount":1,"bathroomCount":null,"des":"一、位置：公寓位于海珠区江泰路A出口步行600米，大马路边。 二、公寓是全新装修的，家具家电都是定制款，全部都是新的，还没人用过。 三、我们的房子分别有：单间套房，一房一厅。我们是专注租房行业的，所以每个房间的格局以及配套都比较合理齐全。所有房间都有带独立大阳台，独立厨房，独立卫生间。 四、配套：我们的公寓已经做到拎包入住条件，为你省去布置新家的烦恼。房间配置：床，衣柜，沙发，茶几，电脑桌，椅子，收纳柜，电视柜，空调，热水器，抽烟机，冰箱，洗衣机等，所有配套都是全新。 五、生活：公寓楼下就有生活超市，小吃，附近有菜市场等，日常生活非常方便。一户一卡门禁管理，安全非常有保障！","metro":"11/10/2/8号线","floor":"低层(共7层)","imgHashes":["2de82e3b6253e5b2db59e0c90f402c82","b616920faf43b49ecc61fd6fc81d15bb","5dd9a0c028bb7cc0de139b4247cfbf37","db4c45521188a169ba0e11fa58918382","0254aae88a0c46bc000fe75a4b7f30ea","615fc80734993a403e1637036ebb94c9","fd405a168364a01210eaab3eaf461fb4"],"amenities":[]},{"id":"7471648831","title":"海珠区中大布匹批发市场，江南西，金紫里美食街，大阳台押一付一","price":1600,"area":"28","orient":"朝南","rentType":"整租","rooms":"1室","roomCount":1,"bathroomCount":null,"des":"一、位置：公寓位于海珠区江泰路A出口步行600米，大马路边。 二、公寓是全新装修的，家具家电都是定制款，全部都是新的，还没人用过。 三、我们的房子分别有：单间套房，一房一厅。我们是专注租房行业的，所以每个房间的格局以及配套都比较合理齐全。所有房间都有带独立大阳台，独立厨房，独立卫生间。 四、配套：我们的公寓已经做到拎包入住条件，为你省去布置新家的烦恼。房间配置：床，衣柜，沙发，茶几，电脑桌，椅子，收纳柜，电视柜，空调，热水器，抽烟机，冰箱，洗衣机等，所有配套都是全新。 五、生活：公寓楼下就有生活超市，小吃，附近有菜市场等，日常生活非常方便。一户一卡门禁管理，安全非常有保障！","metro":"11/10/2/8号线","floor":"高层(共7层)","imgHashes":["2413b9ca3b2f868f41ac17d0844751dd","902c1caf2104d7d3d120423bacc121af","68ba917969b4e10f540945c159b12e6d","bff98e6b79c3017772393c139206332e","39d0eed7951b85ff7b21296c9f6fcac7","ebb1f1d6d0a1cd35e46803c1a928230e","68c94b4ae90a7e302d02bf0378824652"],"amenities":[]},{"id":"7456511042","title":"海珠区江泰路泰沙路金紫里美食街一房一厅精装修，大马路拎包入住","price":1980,"area":"45","orient":"朝南","rentType":"整租","rooms":"1室1厅","roomCount":1,"bathroomCount":null,"des":"一、位置：公寓位于海珠区江泰路A出口步行600米，大马路边。 二、公寓是全新装修的，家具家电都是定制款，全部都是新的，还没人用过。 三、我们的房子分别有：单间套房，一房一厅。我们是专注租房行业的，所以每个房间的格局以及配套都比较合理齐全。所有房间都有带独立大阳台，独立厨房，独立卫生间。 四、配套：我们的公寓已经做到拎包入住条件，为你省去布置新家的烦恼。房间配置：床，衣柜，沙发，茶几，电脑桌，椅子，收纳柜，电视柜，空调，热水器，抽烟机，冰箱，洗衣机等，所有配套都是全新。 五、生活：公寓楼下就有生活超市，小吃，附近有菜市场等，日常生活非常方便。一户一卡门禁管理，安全非常有保障！","metro":"11/10/2/8号线","floor":"中层(共6层)","imgHashes":["3bb0d175e0b551652bb9dbf12541d6be","976ef7fbfba14451c0f6f14d3a1b9b0b","e8a25894a2e0947b26a0d1e49275106c","be39fc2c0406240cc56608955cb8a0a3","ed1d578632430e72b151a311f147b324","2f123887412e598119af4c86d78ed9f0","b973179fb5cbbad4a80522b17284fcac"],"amenities":[]},{"id":"7471648821","title":"海珠区中大，江泰路，泰沙路大单间带阳台，拎包入住，家电齐全","price":1600,"area":"28","orient":"朝南","rentType":"整租","rooms":"1室","roomCount":1,"bathroomCount":null,"des":"一、位置：公寓位于海珠区江泰路A出口步行600米，大马路边。 二、公寓是全新装修的，家具家电都是定制款，全部都是新的，还没人用过。 三、我们的房子分别有：单间套房，一房一厅。我们是专注租房行业的，所以每个房间的格局以及配套都比较合理齐全。所有房间都有带独立大阳台，独立厨房，独立卫生间。 四、配套：我们的公寓已经做到拎包入住条件，为你省去布置新家的烦恼。房间配置：床，衣柜，沙发，茶几，电脑桌，椅子，收纳柜，电视柜，空调，热水器，抽烟机，冰箱，洗衣机等，所有配套都是全新。 五、生活：公寓楼下就有生活超市，小吃，附近有菜市场等，日常生活非常方便。一户一卡门禁管理，安全非常有保障！","metro":"11/10/2/8号线","floor":"中层(共7层)","imgHashes":["8884a1702d72a50e0c42ca44292c26fe","feff17b2eff87108ee3fc2eb681dcff3","d94c00be6a2e586fd2f8e2613422802a","71b597840d4f8774bbddb0dfc03f147e","b42e4b1d6d43a24d015eaee00af52e1f","918e11822bc8afc93ddfe5627e2f176b","7317bf9fe1a2da90c73e4222248a968d"],"amenities":[]},{"id":"7471470510","title":"中大布匹市场，服装批发，江泰路，泰沙路，金紫里美食街拎包入住","price":1500,"area":"30","orient":"朝南","rentType":"整租","rooms":"1室1厅","roomCount":1,"bathroomCount":null,"des":"一、位置：公寓位于海珠区江泰路A出口步行600米，大马路边。 二、公寓是全新装修的，家具家电都是定制款，全部都是新的，还没人用过。 三、我们的房子分别有：单间套房，一房一厅。我们是专注租房行业的，所以每个房间的格局以及配套都比较合理齐全。所有房间都有带独立大阳台，独立厨房，独立卫生间。 四、配套：我们的公寓已经做到拎包入住条件，为你省去布置新家的烦恼。房间配置：床，衣柜，沙发，茶几，电脑桌，椅子，收纳柜，电视柜，空调，热水器，抽烟机，冰箱，洗衣机等，所有配套都是全新。 五、生活：公寓楼下就有生活超市，小吃，附近有菜市场等，日常生活非常方便。一户一卡门禁管理，安全非常有保障！","metro":"11/10/2/8号线","floor":"低层(共7层)","imgHashes":["a490e4adc96e5b151ffc818b2c469fb6","ca62b38e965967637468c06ca9bb084b","3ec0f9257becc5cdbc7d9b15799df249","c180056eb8431ffedc1bf10c2546e9a8","cf5f2e1afa4d282287ab2fbe36d73d64","6f982abfbaf61221fed65c8f10b2fbe4","76e12ed9715fe9f9e94f26a132cbbf3c"],"amenities":[]},{"id":"7471648808","title":"中大布匹市场，服装批发，江泰路，泰沙路，金紫里美食街拎包入住","price":1500,"area":"30","orient":"朝南","rentType":"整租","rooms":"1室1厅","roomCount":1,"bathroomCount":null,"des":"一、位置：公寓位于海珠区江泰路A出口步行600米，大马路边。 二、公寓是全新装修的，家具家电都是定制款，全部都是新的，还没人用过。 三、我们的房子分别有：单间套房，一房一厅。我们是专注租房行业的，所以每个房间的格局以及配套都比较合理齐全。所有房间都有带独立大阳台，独立厨房，独立卫生间。 四、配套：我们的公寓已经做到拎包入住条件，为你省去布置新家的烦恼。房间配置：床，衣柜，沙发，茶几，电脑桌，椅子，收纳柜，电视柜，空调，热水器，抽烟机，冰箱，洗衣机等，所有配套都是全新。 五、生活：公寓楼下就有生活超市，小吃，附近有菜市场等，日常生活非常方便。一户一卡门禁管理，安全非常有保障！","metro":"11/10/2/8号线","floor":"低层(共7层)","imgHashes":["ca62b38e965967637468c06ca9bb084b","a490e4adc96e5b151ffc818b2c469fb6","3ec0f9257becc5cdbc7d9b15799df249","c180056eb8431ffedc1bf10c2546e9a8","cf5f2e1afa4d282287ab2fbe36d73d64","6f982abfbaf61221fed65c8f10b2fbe4","76e12ed9715fe9f9e94f26a132cbbf3c"],"amenities":[]},{"id":"7465487813","title":"海珠区，中大布匹市场，轻纺城，瑞宝，东晓南，南洲拎包入住","price":1200,"area":"25","orient":"朝南","rentType":"整租","rooms":"1室","roomCount":1,"bathroomCount":null,"des":"一、位置：公寓位于海珠区江泰路A出口步行600米，大马路边。  二、公寓是全新装修的，家具家电都是定制款，全部都是新的，还没人用过。  三、我们的房子分别有：单间套房，一房一厅。我们是专注租房行业的，所以每个房间的格局以及配套都比较合理齐全。所有房间都有带独立大阳台，独立厨房，独立卫生间。  四、配套：我们的公寓已经做到拎包入住条件，为你省去布置新家的烦恼。房间配置：床，衣柜，沙发，茶几，电脑桌，椅子，收纳柜，电视柜，空调，热水器，抽烟机，冰箱，洗衣机等，所有配套都是全新。  五、生活：公寓楼下就有生活超市，小吃，附近有菜市场等，日常生活非常方便。一户一卡门禁管理，安全非常有保障！","metro":"11/10/2/8号线","floor":"低层(共7层)","imgHashes":["9e18d3d0b5b09bfa17cb5b48acd17d6e","89f5d9a7b385850075608252b1fc534e","67fa04426a7315efde628737b50bab8a","e48c890beceaa5424c7d7bb6468b4043","e50f5c19955c3e5cfa1a2bb0f42971c9","b84c966bb991aa353770fdb7da747e68","cc29a28472cd2861a62118edb3abb073","23445f588dc49c6c880795a0632d3e68"],"amenities":[]},{"id":"7457440131","title":"海珠区中大国际市场，东晓南，瑞宝，江泰路，金紫里，泰沙路单间","price":1500,"area":"25","orient":"朝南","rentType":"整租","rooms":"1室","roomCount":1,"bathroomCount":null,"des":"一、位置：公寓位于海珠区江泰路A出口步行600米，大马路边。 二、公寓是全新装修的，家具家电都是定制款，全部都是新的，还没人用过。 三、我们的房子分别有：单间套房，一房一厅。我们是专注租房行业的，所以每个房间的格局以及配套都比较合理齐全。所有房间都有带独立大阳台，独立厨房，独立卫生间。 四、配套：我们的公寓已经做到拎包入住条件，为你省去布置新家的烦恼。房间配置：床，衣柜，沙发，茶几，电脑桌，椅子，收纳柜，电视柜，空调，热水器，抽烟机，冰箱，洗衣机等，所有配套都是全新。 五、生活：公寓楼下就有生活超市，小吃，附近有菜市场等，日常生活非常方便。一户一卡门禁管理，安全非常有保障！","metro":"11/10/2/8号线","floor":"低层(共7层)","imgHashes":["2de82e3b6253e5b2db59e0c90f402c82","db4c45521188a169ba0e11fa58918382","b616920faf43b49ecc61fd6fc81d15bb","0254aae88a0c46bc000fe75a4b7f30ea","5dd9a0c028bb7cc0de139b4247cfbf37","615fc80734993a403e1637036ebb94c9","fd405a168364a01210eaab3eaf461fb4"],"amenities":[]},{"id":"7457440080","title":"海珠区江泰路泰沙路金紫里美食街一房一厅精装修，大马路拎包入住","price":1980,"area":"45","orient":"朝南","rentType":"整租","rooms":"1室1厅","roomCount":1,"bathroomCount":null,"des":"一、位置：公寓位于海珠区江泰路A出口步行600米，大马路边。 二、公寓是全新装修的，家具家电都是定制款，全部都是新的，还没人用过。 三、我们的房子分别有：单间套房，一房一厅。我们是专注租房行业的，所以每个房间的格局以及配套都比较合理齐全。所有房间都有带独立大阳台，独立厨房，独立卫生间。 四、配套：我们的公寓已经做到拎包入住条件，为你省去布置新家的烦恼。房间配置：床，衣柜，沙发，茶几，电脑桌，椅子，收纳柜，电视柜，空调，热水器，抽烟机，冰箱，洗衣机等，所有配套都是全新。 五、生活：公寓楼下就有生活超市，小吃，附近有菜市场等，日常生活非常方便。一户一卡门禁管理，安全非常有保障！","metro":"11/10/2/8号线","floor":"中层(共6层)","imgHashes":["b0b9c2c5c549c82d3ce48cd5a9699ad5","808dbccca689a5147bbb24b76add3a6d","e8a25894a2e0947b26a0d1e49275106c","2f123887412e598119af4c86d78ed9f0","ed1d578632430e72b151a311f147b324","b973179fb5cbbad4a80522b17284fcac","f7b1c890419ad9fa4d87b51134e4bc8e"],"amenities":[]},{"id":"7451521662","title":"海珠区江泰路泰沙路金紫里瑞宝东晓南大阳台拎包入住无遮挡采光好","price":1600,"area":"28","orient":"朝南","rentType":"整租","rooms":"1室","roomCount":1,"bathroomCount":null,"des":"一、位置：公寓位于海珠区江泰路A出口步行600米，大马路边。  二、公寓是全新装修的，家具家电都是定制款，全部都是新的，还没人用过。  三、我们的房子分别有：单间套房，一房一厅。我们是专注租房行业的，所以每个房间的格局以及配套都比较合理齐全。所有房间都有带独立大阳台，独立厨房，独立卫生间。  四、配套：我们的公寓已经做到拎包入住条件，为你省去布置新家的烦恼。房间配置：床，衣柜，沙发，茶几，电脑桌，椅子，收纳柜，电视柜，空调，热水器，抽烟机，冰箱，洗衣机等，所有配套都是全新。  五、生活：公寓楼下就有生活超市，小吃，附近有菜市场等，日常生活非常方便。一户一卡门禁管理，安全非常有保障！","metro":"11/10/2/8号线","floor":"中层(共7层)","imgHashes":["60dbbfd13fe74ea458fc81a6beead8ad","49d5bde48d4fbfbe3e1f3ebe8a05eccc","7707e9c066a7cb29b1ee6ee47a80aefa","bfac86f42587b88b3ef266fe237c8a5f","5c8eaaf41fc8f72a05dd30c2bdadc11f","08cb0f1483afc50d50ddd48c7541d194","50056c53c9767402aa5303ecba70d632"],"amenities":[]},{"id":"7448089547","title":"江泰路泰沙路金紫里瑞宝东晓南押一付一，一房一厅大阳台拎包入住","price":1880,"area":"45","orient":"朝南","rentType":"整租","rooms":"1室1厅","roomCount":1,"bathroomCount":null,"des":"一、位置：公寓位于大石A出口步行300米，大马路边。  二、公寓是全新装修的，家具家电都是定制款，全部都是新的，还没人用过。  三、我们的房子分别有：单间套房，一房一厅。我们是专注租房行业的，所以每个房间的格局以及配套都比较合理齐全。所有房间都有带独立大阳台，独立厨房，独立卫生间。  四、配套：我们的公寓已经做到拎包入住条件，为你省去布置新家的烦恼。房间配置：床，衣柜，沙发，茶几，电脑桌，椅子，收纳柜，电视柜，空调，热水器，抽烟机，冰箱，洗衣机等，所有配套都是全新。  五、生活：公寓楼下就有生活超市，小吃，附近有菜市场等，日常生活非常方便。一户一卡门禁管理，安全非常有保障！","metro":"11/10/2/8号线","floor":"中层(共6层)","imgHashes":["e634133645f0f8c640304d5cb6b9e092","0e4d01181a1297466bf691c47a1f7b61","12a2e0e46f66d712b1b5ded3b7e2d5f2","7e2387cad55e5638d95b9b25d7f99ffe","77f5f87197ceefe16bcffbc8b5920284","bf53e40deb67cb35d57c73d9f410526e","07c8efad1ce7aacae400d406cc583d12"],"amenities":[]},{"id":"7448084794","title":"海珠区江泰路金紫里地铁站口，大马路交通方便，拎包入住家电齐全","price":1880,"area":"40","orient":"朝南","rentType":"整租","rooms":"1室1厅","roomCount":1,"bathroomCount":null,"des":"一、位置：公寓位于海珠区江泰路A出口步行600米，大马路边。  二、公寓是全新装修的，家具家电都是定制款，全部都是新的，还没人用过。  三、我们的房子分别有：单间套房，一房一厅。我们是专注租房行业的，所以每个房间的格局以及配套都比较合理齐全。所有房间都有带独立大阳台，独立厨房，独立卫生间。  四、配套：我们的公寓已经做到拎包入住条件，为你省去布置新家的烦恼。房间配置：床，衣柜，沙发，茶几，电脑桌，椅子，收纳柜，电视柜，空调，热水器，抽烟机，冰箱，洗衣机等，所有配套都是全新。  五、生活：公寓楼下就有生活超市，小吃，附近有菜市场等，日常生活非常方便。一户一卡门禁管理，安全非常有保障！","metro":"11/10/2/8号线","floor":"中层(共7层)","imgHashes":["1d65a4035bd8386cc05e8f74ebf598aa","d0664f23d7cb74b845676cac09e7f45e","82a683dee7dfa24d29f5c7dcddd61005","8ba5cd5a30827c5d9a41955a3af230fa","287fbec5d75642ffcddeb4ecc7d7d47f","d13a4af60b7c60055be50f0002fadf75"],"amenities":[]},{"id":"7440187489","title":"海珠区江泰路泰沙路金紫里瑞宝东晓南南洲单间出租，拎包入住家电","price":1400,"area":"25","orient":"朝南","rentType":"整租","rooms":"1室","roomCount":1,"bathroomCount":null,"des":"一、位置：公寓位于海珠区江泰路A出口步行600米，大马路边。  二、公寓是全新装修的，家具家电都是定制款，全部都是新的，还没人用过。  三、我们的房子分别有：单间套房，一房一厅。我们是专注租房行业的，所以每个房间的格局以及配套都比较合理齐全。所有房间都有带独立大阳台，独立厨房，独立卫生间。  四、配套：我们的公寓已经做到拎包入住条件，为你省去布置新家的烦恼。房间配置：床，衣柜，沙发，茶几，电脑桌，椅子，收纳柜，电视柜，空调，热水器，抽烟机，冰箱，洗衣机等，所有配套都是全新。  五、生活：公寓楼下就有生活超市，小吃，附近有菜市场等，日常生活非常方便。一户一卡门禁管理，安全非常有保障！","metro":"11/10/2/8号线","floor":"中层(共6层)","imgHashes":["1cbb5c135dc4c2c8506585fabfcb1921","b27bca43447f0a39c73b30949816eb6b","d650ff88de76bacf61b1b2d6c24b7487","8fa1438ba1aff0fc151fecb80401f7fd","9ed8e6f80b8b112430c667cf49c79a5e","dee405d21cf9656f71d298a183f686ba","3d1a45527d4cce44b6c70ad13dffa70f"],"amenities":[]},{"id":"7432959478","title":"海珠区江泰路泰沙路金紫里牌坊瑞宝东晓南南洲凤阳街道单间出租","price":1400,"area":"28","orient":"朝南","rentType":"整租","rooms":"1室","roomCount":1,"bathroomCount":null,"des":"一、位置：公寓位于海珠区江泰路A出口步行600米，大马路边。  二、公寓是全新装修的，家具家电都是定制款，全部都是新的，还没人用过。  三、我们的房子分别有：单间套房，一房一厅。我们是专注租房行业的，所以每个房间的格局以及配套都比较合理齐全。所有房间都有带独立大阳台，独立厨房，独立卫生间。  四、配套：我们的公寓已经做到拎包入住条件，为你省去布置新家的烦恼。房间配置：床，衣柜，沙发，茶几，电脑桌，椅子，收纳柜，电视柜，空调，热水器，抽烟机，冰箱，洗衣机等，所有配套都是全新。  五、生活：公寓楼下就有生活超市，小吃，附近有菜市场等，日常生活非常方便。一户一卡门禁管理，安全非常有保障！","metro":"11/10/2/8号线","floor":"中层(共6层)","imgHashes":["1dfd48f0500e78a1143d0feb365035c8","d9d805a9e8d61545c82b0e8f3670b03e","8cda3d13a80bfd0cf2baa92d26614455","94419a6dd06bf25b71badb3414e88942","1f866e76d0fbd17b95366db03ec7bf1d","0853fcb02002334c702437319544c573","5a6ce6c88a86166d3844835f16fe9f74"],"amenities":[]},{"id":"7409807110","title":"中大布匹市场，地铁2号线江泰路，单间押一付一短租长租拎包入住","price":1500,"area":"25","orient":"朝南","rentType":"整租","rooms":"1室","roomCount":1,"bathroomCount":null,"des":"一、位置：公寓位于海珠区江泰路A出口步行600米，大马路边。  二、公寓是全新装修的，家具家电都是定制款，全部都是新的，还没人用过。  三、我们的房子分别有：单间套房，一房一厅。我们是专注租房行业的，所以每个房间的格局以及配套都比较合理齐全。所有房间都有带独立大阳台，独立厨房，独立卫生间。  四、配套：我们的公寓已经做到拎包入住条件，为你省去布置新家的烦恼。房间配置：床，衣柜，沙发，茶几，电脑桌，椅子，收纳柜，电视柜，空调，热水器，抽烟机，冰箱，洗衣机等，所有配套都是全新。  五、生活：公寓楼下就有生活超市，小吃，附近有菜市场等，日常生活非常方便。一户一卡门禁管理，安全非常有保障！","metro":"11/10/2/8号线","floor":"中层(共7层)","imgHashes":["fe2d22e84b84fe97ba2cfc76f2bf76e3","399db0f19d425000f6ead486b2bd046b","586cdf7dbb99b400a337fef437f8cb70","769e01f1c94258bd682b549848f72329","e6bc209345602f6046c8eb07e268cbed","7c8fccd786d2f001a509b7ceef8fe284","dbdf6debf5f7ce9e8d7616c989c1c135"],"amenities":[]},{"id":"7386412975","title":"海珠区中大布匹市场，轻纺城，瑞宝，东晓南，凤阳，金紫里牌坊","price":1500,"area":"28","orient":"朝南","rentType":"整租","rooms":"1室","roomCount":1,"bathroomCount":null,"des":"一、位置：公寓位于海珠区江泰路A出口步行600米，大马路边。  二、公寓是全新装修的，家具家电都是定制款，全部都是新的，还没人用过。  三、我们的房子分别有：单间套房，一房一厅。我们是专注租房行业的，所以每个房间的格局以及配套都比较合理齐全。所有房间都有带独立大阳台，独立厨房，独立卫生间。  四、配套：我们的公寓已经做到拎包入住条件，为你省去布置新家的烦恼。房间配置：床，衣柜，沙发，茶几，电脑桌，椅子，收纳柜，电视柜，空调，热水器，抽烟机，冰箱，洗衣机等，所有配套都是全新。  五、生活：公寓楼下就有生活超市，小吃，附近有菜市场等，日常生活非常方便。一户一卡门禁管理，安全非常有保障！","metro":"11/10/2/8号线","floor":"高层(共6层)","imgHashes":["bfc579807c258695523a24c06128b5e1","bef23a429da55127e175e0bdbcf10671","5bfbc62306e4a5ccad71d36faeee4dde","429e449fc5df747126c0091b901502b0","2bae14ccbdff33d6067731a07707040e","3f6320140e16a54e9bded4e4c33c812c","19c5f6f43299cae5e30a696c4499848c"],"amenities":[]},{"id":"7463613287","title":"海珠江泰路泰沙路金紫里直街瑞宝东晓南南洲，单间精装修押一付一","price":1500,"area":"25","orient":"朝南","rentType":"整租","rooms":"1室","roomCount":1,"bathroomCount":null,"des":"一、位置：公寓位于海珠区江泰路A出口步行600米，大马路边。  二、公寓是全新装修的，家具家电都是定制款，全部都是新的，还没人用过。  三、我们的房子分别有：单间套房，一房一厅。我们是专注租房行业的，所以每个房间的格局以及配套都比较合理齐全。所有房间都有带独立大阳台，独立厨房，独立卫生间。  四、配套：我们的公寓已经做到拎包入住条件，为你省去布置新家的烦恼。房间配置：床，衣柜，沙发，茶几，电脑桌，椅子，收纳柜，电视柜，空调，热水器，抽烟机，冰箱，洗衣机等，所有配套都是全新。  五、生活：公寓楼下就有生活超市，小吃，附近有菜市场等，日常生活非常方便。一户一卡门禁管理，安全非常有保障！","metro":"11/10/2/8号线","floor":"低层(共6层)","imgHashes":["333c5adac45b84adf33402baf48c789c","0ea2a2fc265485359b8cdffab2b4cb54","83372ba7cd4b16aa273f5c9326b4c1b6","b9b7a83612cc1829023a6a5ae24e793f","e15c937298d721ddc88a56fe0120e12c","a4a298ce979457b2e7a823b04428fdd5","4debc10193e5aa1773b2d245a0cd964a"],"amenities":[]},{"id":"7395447765","title":"海珠区江泰路水边街精装修一房一厅押一付一，拎包入住家电齐全","price":1680,"area":"40","orient":"朝南","rentType":"整租","rooms":"1室1厅","roomCount":1,"bathroomCount":null,"des":"一、位置：公寓位于海珠区江泰路A出口步行600米，大马路边。  二、公寓是全新装修的，家具家电都是定制款，全部都是新的，还没人用过。  三、我们的房子分别有：单间套房，一房一厅。我们是专注租房行业的，所以每个房间的格局以及配套都比较合理齐全。所有房间都有带独立大阳台，独立厨房，独立卫生间。  四、配套：我们的公寓已经做到拎包入住条件，为你省去布置新家的烦恼。房间配置：床，衣柜，沙发，茶几，电脑桌，椅子，收纳柜，电视柜，空调，热水器，抽烟机，冰箱，洗衣机等，所有配套都是全新。  五、生活：公寓楼下就有生活超市，小吃，附近有菜市场等，日常生活非常方便。一户一卡门禁管理，安全非常有保障！","metro":"11/10/2/8号线","floor":"中层(共6层)","imgHashes":["6b2c5b20621fc99af2698acf039de246","a083da1a522e68678d1286a7f56eba6d","aaa1b78959f4b7e4185ce34efa822df2","a94d74f7a2b0fa9c7dfcc8ea2c5a47e8","0c47bddd88f3635cc732457ce99046ad","5bbc88a635818893ebdeb0c18d71e6f9","1db92edf0ca5018c983e3b2f23b68f27"],"amenities":[]},{"id":"2959300216183816","title":"金紫里直街小区 3室1厅1卫","price":3000,"area":"74","orient":"朝南","rentType":"整租","rooms":"3室1厅","roomCount":3,"bathroomCount":1,"des":"","metro":"11/10/2/8号线","floor":"高层(共9层)","imgHashes":[],"amenities":[]},{"id":"7463765916","title":"江泰路 五凤双地铁 路边电梯 民用水电 押一付一 拎包入住","price":1500,"area":"40","orient":"朝南","rentType":"整租","rooms":"1室1厅","roomCount":1,"bathroomCount":null,"des":"• 位于金紫里直街22、23号的精装修一室一厅一卫，带电梯，面积30平米，南向采光好。小区环境优雅，周边生活设施齐全，步行40米即达佳南平价超市，购物方便。附近有蓝天中学公交站（165米），五凤乡站（173米），瑞宝乡站（196米），凤阳街道政务中心站（227米），交通便利。距离10号线五凤地铁站927米，11号线五凤地铁站943米，出行无忧。广州致友医院696米，医疗有保障。押一付一，整租，随时可看房，欢迎咨询！","metro":"11/10/2/8号线","floor":"中层(共8层)","imgHashes":["c2817c08efa58400f9566bc749c04767","f5cdf01f68d427149564d38d7e80bc67","4fb25f020d84d9ab4c27bf2e3fa1f15e","65a9037eecc882707f2bb053d47b53f2","8f3ffe98385660ca1be96e7a1a3fc05a","dd5fc67909640da75adfc6b21c3995d6","b332b77d0193bf075d7eb266ef8c66de","af008e0e713fc5332302c6fad2348139"],"amenities":[]}]