[{"id":7381219490,"title":"黄村近地铁 奥体中心 优托邦 中海康城 尚北科创园 东澳小镇","price":800,"area":"50","orient":"朝南","rentType":"整租","rooms":"1室","roomCount":1,"bathroomCount":null,"des":"黄村地铁站附近，押一付一，民用水电，全新装修，家私家电齐，拎包入住。  周边大市场，大型超市，商业步行街。生活休闲都方便  门襟卡出入，24小时双门卫，安全可靠。  房间都是南北通透，独立厨房卫生间大阳台，采光好，交通便利。","metro":"","floor":"高层(共7层)","imgHashes":["bfa147fccd0bdf4c2fff5861d688045e","c696336e8629722df28f24249fde78fc","13d5a9d43b2b333278c261e3a1bdffe9","77461f08e2f3043f10bd49eb247b9d21","050dba99c7385d3f2ac3d815cce23776","2517e2cf17f1fba8ef672bd4be41cbf4","e6fa54b75b1394c593398d9886ad789e","8a4b0a3e7554f1f58641111a68ccceed"],"amenities":["fridge","washing_machine","water_heater","wifi","sofa","range_hood","gas_stove","cooking_ok","tv","ac","wardrobe","bed","bathroom","smart_lock","balcony","heating"]},{"id":7388920777,"title":"天河区华实学校旁有电梯阳光单间，家电齐全拎包入住","price":1380,"area":"28","orient":"朝南","rentType":"整租","rooms":"1室","roomCount":1,"bathroomCount":null,"des":"本有天河区华实学校旁有精装修的阳光大单间，采光好无遮挡家电齐全拎包入住","metro":"","floor":"中层(共8层)","imgHashes":["8009f3ca9f4530b575ab48e01d003850","e50d4c91f3a4b7622da8ed889d57d2c0","b5b87aa1efb81308a2480b6445acae95","a53960672bd541747b6f3c36d8c9853d","13734d2e7be611f09b8dc7df938e8ce8","73df92c1b21e231d30815c95a6808a2f","98c51581f4b0d077fd5ebc4aac0ad4f9","275f5321093826ca655c77f75446bcfb"],"amenities":["fridge","washing_machine","water_heater","wifi","sofa","range_hood","gas_stove","cooking_ok","tv","ac","wardrobe","bed","bathroom","smart_lock","balcony","heating"]},{"id":7372596489,"title":"黄村地铁 东英科技园 奥体优托邦 精装修公寓大单间 电梯","price":1380,"area":"60","orient":"朝南","rentType":"整租","rooms":"1室","roomCount":1,"bathroomCount":null,"des":"房子环境优美,绿化充足,入住即与精英为邻交通便利,附近的公交：B1路、B2A路、B3路、B4路、B4B路、B5路、B6路、B7路、B15路、B16路、B17路、B18路、B19路、B20路、B27路地铁：4号线黄村站公交：B1路、B2A路、B3路、B4路、B4B路、B5路、B6路、B7路、B15路、B16路、B17路、B18路、B19路、B20路、B27路地铁：4号线黄村站,天河区BRT直达，4号地铁线，5号线地铁有小区房，有公寓房。有合租，有整租。有单间，一房，两房和三房。有精装修有普通装修。都是家私电器齐全，可以拎包入住！光线通风好。大路边不走巷子，安全安静。交通便捷","metro":"","floor":"中层(共10层)","imgHashes":["26a3c899bbc440b111d34080083af01c","f3724fb93b1899be61fc809618e60400","f9a818024f62ec188b2d63d028a732e0","4cbb021d8ce0f72e9d1a01b8724882b6","1af36da5aca3fe3ee7545b5f754f8218","58573237b88b66bd78c9b16e3a085a65","ecee674f4ddd930269dccf27a265f19e","d7eb013c53dc4ad43c79d3fe7ce2b5e6"],"amenities":["fridge","washing_machine","water_heater","wifi","sofa","range_hood","gas_stove","cooking_ok","ac","wardrobe","bed","bathroom","smart_lock","balcony","heating"]},{"id":7372314928,"title":"黄村地铁 精装修社区环境大单间 民用水电","price":1000,"area":"38","orient":"朝东","rentType":"整租","rooms":"1室","roomCount":1,"bathroomCount":null,"des":"1、为您在广州有一个温馨舒适的家!选材低碳环保，配套设施完善，拎包即可入住;2、房间明亮方正，通风采光好，空气对流，位置安静，有独立卫生间、厨房;配有家私家电:空调，洗衣机，冰箱、热水器，油烟机，衣柜，沙发，桌椅，高档实木超大床，家电网络齐全，通风采光好。小区还有全天候的楼道管理系统、出入口的电子门禁系统等;3、温馨、精致、舒适，小资生活情调，为-青年白领有良好的人际交往的平台;4、周边遍布风味小吃、夜宵及大型商场，在繁忙的工作之余，给你带来丰富的休闲享受;5、随时入住，随时欢迎您的来电呀6.贴心的带看  好服务，根据需求推荐更多性价比高的房子7.可以加我朋友  圈有大量房源出租","metro":"","floor":"中层(共6层)","imgHashes":["5c265f9f95b2dd38f7f9d95d3ae86e82","56ed76920e4e25a3530f1f358a314501","1ea6b8cfd86b0547ed2c2b9cfb5fa3b2","2fd59d37d7164ecbbd57531840ab33e6","abc5c5281250e8950f7d6d2a602b34f3","6eb71baf678fee7cfc6ae929d4b51968","416ab1609b435eefbb23cc844a394acc"],"amenities":["fridge","washing_machine","water_heater","wifi","sofa","range_hood","cooking_ok","ac","wardrobe","bed","bathroom","smart_lock","balcony","heating"]},{"id":7372299464,"title":"黄村社区精装修大单间 优托邦 天银大厦 学生毕业季，民用水电","price":1500,"area":"45","orient":"朝南","rentType":"整租","rooms":"1室","roomCount":1,"bathroomCount":null,"des":"1、为您在广州有一个温馨舒适的家!选材低碳环保，配套设施完善，拎包即可入住;2、房间明亮方正，通风采光好，空气对流，位置安静，有独立卫生间、厨房;配有家私家电:空调，洗衣机，冰箱、热水器，油烟机，衣柜，沙发，桌椅，高档实木超大床，家电网络齐全，通风采光好。小区还有全天候的楼道管理系统、出入口的电子门禁系统等;3、温馨、精致、舒适，小资生活情调，为-青年白领有良好的人际交往的平台;4、周边遍布风味小吃、夜宵及大型商场，在繁忙的工作之余，给你带来丰富的休闲享受;5、随时入住，随时欢迎您的来电呀6.贴心的带看  好服务，根据需求推荐更多性价比高的房子7.可以加我朋友  圈有大量房源出租","metro":"","floor":"中层(共8层)","imgHashes":["3fa1fd3b3b39b1283f78030ac40d60ab","abd437037d0db91ba7fae01aff8e153c","bc851c7af606fbbf379e81c8622531e1","3e14497f94dfecb0287e368d51867e1d","c3d221ef8fc27e0dfeccad6f1d912095","caf625ac135a1348611909e46d24c70d","8f9f345b6bba48c1a5238e4f47fa9a74","176b9d50e8ef8821c501fa95fd1d6459"],"amenities":["fridge","washing_machine","water_heater","wifi","sofa","range_hood","cooking_ok","ac","wardrobe","bed","smart_lock","balcony","heating"]},{"id":7369106672,"title":"黄村地铁豪华大单间 裕景工业园 神舟路 天河智慧城 科学城","price":1500,"area":"50","orient":"朝东","rentType":"整租","rooms":"1室","roomCount":1,"bathroomCount":null,"des":"房子环境优美，绿化充足，入住即与精英为邻交通便利，附近的公交：B1路、B2A路、B3路、B4路、B4B路、B5路、B6路、B7路、B15路、B16路、B17路、B18路、B19路、B20路、B27路地铁：4号线黄村站公交：B1路、B2A路、B3路、B4路、B4B路、B5路、B6路、B7路、B15路、B16路、B17路、B18路、B19路、B20路、B27路地铁：4号线黄村站，天河区BRT直达，4号地铁线，5号线地  铁有小区房，有公寓房。有合租，有整租。有单间，一房，两房和三房。有精装修有普通装修。都是家私电器齐全，可以拎包入住！光线通风好。大路边不走巷子安全安静。交通便捷","metro":"","floor":"中层(共8层)","imgHashes":["c1809e6ebfba30342a1fc3c70ada0675","9f607e059225453976b95a68e15609f1","604a7a8de52e83b80bb88fbbb968abd1","85cfc4781c5f6522807bb3bea27b0c95","92f541255e81168794a3764e82f377d4","83f8a9b67ab8429dc7d9062adbdd76ae"],"amenities":["fridge","washing_machine","water_heater","wifi","sofa","range_hood","gas_stove","cooking_ok","ac","wardrobe","bed","bathroom","smart_lock","balcony","heating"]},{"id":7388915403,"title":"天河区珠村华实学校边有电梯大单间采光好，家电齐全拎包入住","price":1680,"area":"42","orient":"朝南","rentType":"整租","rooms":"1室","roomCount":1,"bathroomCount":null,"des":"本天河区珠村华实学校旁阳光单间家电齐全拎包入住","metro":"","floor":"中层(共8层)","imgHashes":["1195962f46ae69e0a59d4c12cffcf941","4829b7861e3d3a4a06823ceff22ce410","10aecd14d715ca548e2e751aee5fff97","60244a0ffee98b2e6bb1abd1aa8731cc","67d2fb4b2ebfe8abee1c47e06f749c94","71c494448b9647396fb42d4e4abf9ef7","ea177ad99cb597651e3da290e4c02530","ba19bcbc30f23ec2c30dabf4b7092ef0"],"amenities":["fridge","washing_machine","water_heater","wifi","sofa","range_hood","gas_stove","cooking_ok","tv","ac","wardrobe","bed","bathroom","smart_lock","balcony","heating"]},{"id":7372297504,"title":"黄村精装修无遮挡大套间 优托邦 东英科技园 民水电拎包入住","price":1500,"area":"60","orient":"朝南","rentType":"整租","rooms":"1室","roomCount":1,"bathroomCount":null,"des":"黄村精装修无遮挡大套间 优托邦 东英科技园 民水电拎包入住","metro":"","floor":"中层(共8层)","imgHashes":["510778f055c93c7e1eb23bb07c640774","b73381c02cdb91da589b1381b6faa73b","2827273d82a96de3a2b136798368d0a0","de6a5c72a931b381951c2a3008ad8e78","b1f864dd9ee21f305c9229ad95645236","f75ab5605ba71c516b0f4adb0070356e","d83a6efda4eb984174346867f9821053","fb85a1f78f23abc088731883f1ffa055"],"amenities":["fridge","washing_machine","water_heater","wifi","sofa","range_hood","cooking_ok","ac","wardrobe","bed","bathroom","smart_lock","balcony","heating"]},{"id":7369103184,"title":"黄村地铁 大灵山路 奥体中心 优托邦 裕景 精装电梯大单间","price":1500,"area":"50","orient":"朝东","rentType":"整租","rooms":"1室","roomCount":1,"bathroomCount":null,"des":"房子环境优美，绿化充足，入住即与精英为邻交通便利，附近的公交：B1路、B2A路、B3路、B4路、B4B路、B5路、B6路、B7路、B15路、B16路、B17路、B18路、B19路、B20路、B27路地铁：4号线黄村站公交：B1路、B2A路、B3路、B4路、B4B路、B5路、B6路、B7路、B15路、B16路、B17路、B18路、B19路、B20路、B27路地铁：4号线黄村站，天河区BRT直达，4号地铁线，5号线地  铁有小区房，有公寓房。有合租，有整租。有单间，一房，两房和三房。有精装修有普通装修。都是家私电器齐全，可以拎包入住！光线通风好。大路边不走巷子安全安静。交通便捷","metro":"","floor":"中层(共8层)","imgHashes":["e756e3b3d169c78e7018f21054493a23","d0d2ab5d5d4ea10a907a7bc821b824d8","4c5e59587d243f6a66f99ed8122ff882","3642ee8cf55ff87ea2533630da84a121","6d5c1aa89a64df36aac10d2d39203dd2","1f54fe0b53c1426c0fa1be2660f93a47","d67c54a08c4bc1f760141c2f40502f0b"],"amenities":["fridge","washing_machine","water_heater","wifi","sofa","range_hood","gas_stove","cooking_ok","ac","wardrobe","bed","bathroom","smart_lock","balcony","heating"]},{"id":7388906035,"title":"天河区珠村有电梯阳光大单间采光好家电齐全拎包入住","price":1880,"area":"46","orient":"朝南","rentType":"整租","rooms":"1室","roomCount":1,"bathroomCount":null,"des":"本有天河区珠村华实学校旁有阳光大单间采光好家电齐全拎包入住","metro":"","floor":"中层(共8层)","imgHashes":["384b8857fdc57c04817f64fae6d37fdc","55d6098f41ef4b801f4429ec80f0107d","1c903605fb708945d94d595594130df1","3687bf5a5bd35aed078e416c561ba590","2eeea52a0e5d3f533816ec85d3bcd801","fa5c85ec3a10b470882242041ccac3e0","d1739910b5b8b9ed02079c2553ea679a","a54f8b36ad8db59c1bfce978690bc901"],"amenities":["fridge","washing_machine","water_heater","wifi","sofa","range_hood","gas_stove","cooking_ok","tv","ac","wardrobe","bed","bathroom","smart_lock","balcony","heating"]},{"id":"7398625323","title":"黄村地铁 大灵山路 裕景 奥体优托邦 包网络带停车位","price":1000,"area":"40","orient":"朝南","rentType":"整租","rooms":"1室","roomCount":1,"bathroomCount":null,"des":"房子环境优美,绿化充足, 入住即与精英为邻 交通便利,附近的公交：B1路、B2A路、B3路、B4路、B4B路、B5路、B6路、B7路、B15路、B16路、B17路、B18路、B19路、B20路、B27路地铁：4号线黄村站公交：B1路、B2A路、B3路、B4路、B4B路、B5路、B6路、B7路、B15路、B16路、B17路、B18路、B19路、B20路、B27路地铁：4号线黄村站, 天河区BRT直达，4号地铁线，5号线地铁 有小区房，有公寓房。 有合租，有整租。 有单间，一房，两房和三房。 有精装修有普通装修。 都是家私电器齐全，可以拎包入住！光线通风好。大路边不走巷子，安全安静。交通便捷","metro":"","floor":"中层(共8层)","imgHashes":["5f787525df636e94749b7b17f12ce9d2","ae29dbbe8d34bdfe859156e028b16b0d","5723f6bbe2c1e3d6c9151df6ea8e97c7","97ead3c7eb4e13914ecf1dcf1d6b42a4","23ac6295528550d3069ba1e11d3370f5","057d90676994b136d271d618db0b2166","385a409d5ec7b1b8b92774e6041b64d9","e6bc94bd145c2825c27963f2c426fe64"],"amenities":["fridge","washing_machine","water_heater","wifi","sofa","range_hood","gas_stove","cooking_ok","ac","wardrobe","bed","bathroom","smart_lock","balcony","heating"]},{"id":7393266401,"title":"吉山幼儿园  吉山公交 珠村550总站 公寓大单间 拎包入住","price":600,"area":"29","orient":"朝南","rentType":"整租","rooms":"1室","roomCount":1,"bathroomCount":null,"des":"可直达珠江新城广州塔天河城上下九北京路交通便利,附近的公交：B1路、B2A路、B3路、B4路、B4B路、B5路、B6路、B7路、B15路、B16路、B17路、B18路、B19路、B20路、B27路地铁：4号线黄村站公交：B1路、B2A路、B3路、B4路、B4B路、B5路、B6路、B7路、B15路、B16路、B17路、B18路、B19路、B20路、B27路地铁：4号线黄村站,有小区房，有公寓房。有单间，一房，两房和三房。都是家私电器齐全，可以拎包入住！光线通风好。大路边不走巷子，安全安静。交通便捷","metro":"","floor":"低层(共9层)","imgHashes":["8c718f9389a1120406fd1c8389e6a94f","c86aeccea05e69591bb0564669ca206d","38089167d6f054ea47e0a51d3a432416","c2fdbfab3e8de2e65749c12cd56bbba1","d254dece830fd96f0e9be14681425985","e49122ee68eff0a6587c0474564e09ab","abdc41770e730276abf65b8bfc20de59"],"amenities":["fridge","washing_machine","water_heater","wifi","sofa","range_hood","cooking_ok","ac","wardrobe","bed","bathroom","smart_lock","balcony"]},{"id":7380350176,"title":"珠村550公交总站  奥体优托邦  黄村地铁附近  公寓单间","price":600,"area":"50","orient":"朝南","rentType":"整租","rooms":"1室","roomCount":1,"bathroomCount":null,"des":"黄村地铁站附近，押一付一，民用水电，全新装修，家私家电齐，拎包入住。  周边大市场，大型超市，商业步行街。生活休闲都方便  门襟卡出入，24小时双门卫，安全可靠。  房间都是南北通透，独立厨房卫生间大阳台，采光好，交通便利。","metro":"","floor":"高层(共6层)","imgHashes":["c866534204858e83dd469daa4eeef917","5bf2eba2d7ab6ff6488f9c672a070236","5e07850cf24c516c98b8ef8bc204e381","82c52a521902e2df3faffd4b1b99a59f","0008e7a970986fe9ec47c0521bf5db10","63c970c7e91ecf1ee26cce6198c85743","3b9aa406975e3190c22ff3aa692f97b5","28384c04f4d7c58dcfddb7eb1ac27086"],"amenities":["fridge","washing_machine","water_heater","wifi","sofa","range_hood","gas_stove","cooking_ok","ac","wardrobe","bed","bathroom","smart_lock","balcony","heating"]},{"id":7374684553,"title":"东英科技园 优托邦 灵山东路 吉山幼儿园 采光通风 拎包入住","price":800,"area":"36","orient":"朝南","rentType":"整租","rooms":"1室","roomCount":1,"bathroomCount":null,"des":"【我们承诺】房，可押一付一。  【交通便利】东圃黄村珠村出门公交临地铁  【房屋情况】智能电子密码锁，随时带看；均摊民用水电煤；WIFI，车位可租。  【房屋设施】冰箱，空调，微波炉；书桌，台灯，大衣柜；洗衣机，热水器，居家电器，一应俱全  宜家风格装修，木地板，管家1对1服务，双周保洁，温暖家居，清新舒适，采光充足，小区环境优美，交通便利，商圈发达，欢迎您的入住。","metro":"","floor":"高层(共8层)","imgHashes":["aa7d1ca2a0b1996ec1e596e4a6290f0f","c9d1e10d63e595cb0d413eb8ab41fbf4","0b2c9c892a6c71d00990dc58970e978d","224598b3fda0d8978289e9002822c791","9eb25021959e0538110df7248b227d7c","0b3a4bd8eb644aa9cb05b2549c2ffa49","0d7f426508409124b533464166457fc1","d03f46c7618815578115746cc1b43168"],"amenities":["fridge","washing_machine","water_heater","wifi","sofa","range_hood","gas_stove","cooking_ok","tv","ac","wardrobe","bed","bathroom","smart_lock","balcony","heating"]},{"id":7372615371,"title":"黄村地铁 东英科技园 路边电梯网红公寓 大单间 拎包入住","price":700,"area":"60","orient":"朝南","rentType":"整租","rooms":"1室","roomCount":1,"bathroomCount":null,"des":"房子环境优美,绿化充足,入住即与精英为邻交通便利,附近的公交：B1路、B2A路、B3路、B4路、B4B路、B5路、B6路、B7路、B15路、B16路、B17路、B18路、B19路、B20路、B27路地铁：4号线黄村站公交：B1路、B2A路、B3路、B4路、B4B路、B5路、B6路、B7路、B15路、B16路、B17路、B18路、B19路、B20路、B27路地铁：4号线黄村站,天河区BRT直达，4号地铁线，5号线地铁有小区房，有公寓房。有合租，有整租。有单间，一房，两房和三房。有精装修有普通装修。都是家私电器齐全，可以拎包入住！光线通风好。大路边不走巷子，安全安静。交通便捷","metro":"","floor":"中层(共7层)","imgHashes":["8ef78c96a29c8770adeb70a4c0e5b9c5","c0f06539fc9238acbff1eb035888be01","0a689b78ec7076617a409fd1341630d5","87eb093e559e7c2a7b0437e6908e45e1","669324e88e04fc63e21918c9fd8e9f59","e01fca862f968f62cab4baa2086ef858","ed91d906d7cc2885658d5331cd038c9b","07f2a71464b9de3e4fc22f2ada53dee6"],"amenities":["fridge","washing_machine","water_heater","wifi","sofa","range_hood","cooking_ok","ac","wardrobe","bed","bathroom","smart_lock","balcony","heating"]},{"id":7371262788,"title":"黄村地铁口 无遮挡大单间 优托邦 奥林匹克中心 园区环境","price":1580,"area":"50","orient":"朝南","rentType":"整租","rooms":"1室","roomCount":1,"bathroomCount":null,"des":"1.为您在广州有一个温馨的家！选材低碳环保，配套齐全，拎包入住  2.房间明亮方正，通风采光好，空气对流，位置安全，有独立卫生间，厨房，配有家私电，空调洗衣机，冰箱热水器，油烟机，衣柜，沙发，桌椅，高档实木大床，家电网络齐全，通风采光好，小区还有全天候24小时管理安保输入电子门禁等  3.温馨舒适，精致，为青年白领，有良好的人际交流平  台  4.周边有大型商场，夜宵以及各种小吃，在繁忙的工作之余，给你带来丰富的休闲之旅","metro":"","floor":"高层(共9层)","imgHashes":["33f14f194f3ce8432415b4c3d03e28ba","05971cc473a36286811dcc7bab84a371","24ec3f808ea891af50b1af0a81998239","b376134143542214af24f68946b4fc07","ef8c4a8f738db49f0ced52a37a24587d","5248516f38c99478d3e22265959fc921"],"amenities":["fridge","washing_machine","water_heater","wifi","sofa","range_hood","gas_stove","cooking_ok","ac","wardrobe","bed","bathroom","smart_lock","balcony","heating"]},{"id":7369109230,"title":"笋盘 黄村珠村地铁裕景科技园珠村550 车站 商住两用大套间","price":1500,"area":"55","orient":"朝东","rentType":"整租","rooms":"1室","roomCount":1,"bathroomCount":null,"des":"1、房子舒适，南北通透，空气流通，阳光充足  2、配有基础的家具、全新空调、全新热水器。大衣柜、洗衣机、席梦思大床、床头柜、衣柜、电脑桌、梳妆台、沙发、茶几、独立洗手间。独立大阳台。拎包入住..  3、配有厨房，可以做饭！精致装修，温馨周到  4、非常安全，独立大楼，进出都需要刷卡门禁、有监控、每  天有阿姨打扫外面的卫生，干净卫生  5、随时可以看房，拎包入住，专人管理，全天监控，可免停车，管理人员随叫随到  6、联系不上时可直接来电","metro":"","floor":"中层(共8层)","imgHashes":["2abe1c59a119582504970b4ca6dbf5fc","d05f9c57ca3872d5e9a3331b76cd09be","8029dfdba0fb7c1042faaebca102a3a6","ad7a99d0ff8979cac891ff43396cfc88","14678d8d6d39a8540c613474d11e28b3","8b56930e40b9df64be0b1c103ca6b95a","2e0f9a3fe0507a6c973a13dd493a4f5f","3670f3e3c064d67931106e1689040e3b"],"amenities":["fridge","washing_machine","water_heater","wifi","sofa","range_hood","gas_stove","cooking_ok","ac","wardrobe","bed","bathroom","smart_lock","balcony","heating"]},{"id":7369105881,"title":"笋盘上新 黄村珠村地铁裕景科技园550车站商住两用大套间","price":1500,"area":"55","orient":"朝东","rentType":"整租","rooms":"1室","roomCount":1,"bathroomCount":null,"des":"1、房子舒适，南北通透，空气流通，阳光充足  2、配有基础的家具、全新空调、全新热水器。大衣柜、洗衣机、席梦思大床、床头柜、衣柜、电脑桌、梳妆台、沙发、茶几、独立洗手间。独立大阳台。拎包入住..  3、配有厨房，可以做饭！精致装修，温馨周到  4、非常安全，独立大楼，进出都需要刷卡门禁、有监控、每  天有阿姨打扫外面的卫生，干净卫生  5、随时可以看房，拎包入住，专人管理，全天监控，可免停车，管理人员随叫随到  6、联系不上时可直接来电","metro":"","floor":"中层(共8层)","imgHashes":["429393aa43d992f6b88ed4fec4616186","79e9a342ab0a2b3dfaf6960cc8dcfd20","751ef9833f856a8aaf21a6acde7a7cb7","76ea1800553ebd5bfcba3a010b64b1f2","23f283e009a9f4b4dde7469dc4a79634","9561d76292b6a1723ea41aaadbaee249","60580c9cf15c0fac0141bf09b2d3a7bd","80f0b2392d04ac003ebcac6c7c977078"],"amenities":["fridge","washing_machine","water_heater","wifi","sofa","range_hood","gas_stove","cooking_ok","ac","wardrobe","bed","bathroom","smart_lock","balcony","heating"]}]